Metadata-Version: 2.1
Name: russian-quotes
Version: 2.1.0
Summary: Quotes of famous people in Russian & English
Author: liner
Author-email: contact.liner999@gmail.com
License: MIT
Project-URL: GitHub, https://github.com/liner-exe/russian_quotes/
Project-URL: Bug Tracker, https://github.com/liner-exe/russian_quotes/issues
Classifier: Programming Language :: Python :: 3
Classifier: Programming Language :: Python :: 3.7
Classifier: Programming Language :: Python :: 3.8
Classifier: Programming Language :: Python :: 3.9
Classifier: Programming Language :: Python :: 3.10
Classifier: Programming Language :: Python :: 3.11
Classifier: License :: OSI Approved :: MIT License
Classifier: Operating System :: OS Independent
License-File: LICENSE
